tai_api/__init__.py
tai_api/cli/commands/__init__.py
tai_api/cli/commands/cmd_auth/__init__.py
tai_api/cli/commands/cmd_auth/database.py
tai_api/cli/commands/cmd_auth/keycloak.py
tai_api/cli/commands/cmd_auth/main.py
tai_api/cli/commands/cmd_dev/__init__.py
tai_api/cli/commands/cmd_dev/main.py
tai_api/cli/commands/cmd_generate/__init__.py
tai_api/cli/commands/cmd_generate/funcs.py
tai_api/cli/commands/cmd_generate/main.py
tai_api/cli/commands/cmd_init/__init__.py
tai_api/cli/commands/cmd_init/docker/dockerfile
tai_api/cli/commands/cmd_init/docker/entrypoint.sh
tai_api/cli/commands/cmd_init/main.py
tai_api/cli/commands/cmd_init/model.py
tai_api/cli/commands/cmd_init/resources/__init__.py
tai_api/cli/commands/cmd_init/resources/exceptions.py
tai_api/cli/commands/cmd_init/resources/handlers.py
tai_api/cli/commands/cmd_init/resources/mcp.py
tai_api/cli/commands/cmd_init/resources/responses.py
tai_api/cli/commands/cmd_mcp/__init__.py
tai_api/cli/commands/cmd_mcp/main.py
tai_api/cli/main.py
tai_api/config.py
tai_api/generators/__init__.py
tai_api/generators/auth/__init__.py
tai_api/generators/auth/db.py
tai_api/generators/auth/keycloak.py
tai_api/generators/auth/templates/db/__init__.py.j2
tai_api/generators/auth/templates/db/auth_router.py.j2
tai_api/generators/auth/templates/db/dependencies.py.j2
tai_api/generators/auth/templates/db/docs_router.py.j2
tai_api/generators/auth/templates/db/jwt.py.j2
tai_api/generators/auth/templates/kc/__init__.py.j2
tai_api/generators/auth/templates/kc/dependencies.py.j2
tai_api/generators/auth/templates/kc/docs_router.py.j2
tai_api/generators/auth/templates/kc/keycloak_router.py.j2
tai_api/generators/auth/templates/kc/login_router.py.j2
tai_api/generators/auth/templates/kc/utils.py.j2
tai_api/generators/main_file/__init__.py
tai_api/generators/main_file/main.py
tai_api/generators/main_file/templates/__dev__.py.j2
tai_api/generators/main_file/templates/__main__.py.j2
tai_api/generators/routers/__init__.py
tai_api-0.2.20.dist-info/METADATA
tai_api-0.2.20.dist-info/WHEEL
tai_api-0.2.20.dist-info/entry_points.txt
tai_api-0.2.20.dist-info/licenses/LICENSE
tai_api-0.2.20.dist-info/RECORD
