Metadata-Version: 2.4
Name: tai-api
Version: 0.2.20
Summary: FastAPI framework with TAI ecosystem integration
License: MIT
License-File: LICENSE
Keywords: fastapi,api,tai,web-framework
Author: MateoSaezMata
Author-email: msaez@triplealpha.in
Requires-Python: >=3.10,<4.0
Classifier: Development Status :: 4 - Beta
Classifier: Intended Audience :: Developers
Classifier: License :: OSI Approved :: MIT License
Classifier: Programming Language :: Python :: 3
Classifier: Programming Language :: Python :: 3.10
Classifier: Programming Language :: Python :: 3.11
Classifier: Programming Language :: Python :: 3.12
Classifier: Framework :: FastAPI
Classifier: Topic :: Internet :: WWW/HTTP
Classifier: Topic :: Software Development :: Libraries :: Application Frameworks
Requires-Dist: asyncpg (>=0.30.0,<1.0)
Requires-Dist: fastapi[standard] (>=0.116.1,<1.0)
Requires-Dist: python-jose (>=3.5.0,<4.0)
Requires-Dist: tai-sql (>=0.3.59,<1.0)
Requires-Dist: uvicorn[standard] (>=0.30.0,<1.0)
Project-URL: Homepage, https://www.triplealpha.in/es/
Project-URL: Issues, https://github.com/triplealpha-innovation/tai-api/issues
Project-URL: Repository, https://github.com/triplealpha-innovation/tai-api
